<?xml version="1.0" encoding="UTF-8" standalone="no"?>
<!DOCTYPE log SYSTEM "logger.dtd">
<log>
<record>
  <date>2020-04-14T05:51:59.080320500Z</date>
  <millis>1586843519080</millis>
  <nanos>320500</nanos>
  <sequence>0</sequence>
  <logger>Example</logger>
  <level>WARNING</level>
  <class>Example</class>
  <method>main</method>
  <thread>1</thread>
  <message>/ by zero</message>
</record>
<record>
  <date>2020-04-14T05:51:59.118195400Z</date>
  <millis>1586843519118</millis>
  <nanos>195400</nanos>
  <sequence>1</sequence>
  <logger>Example</logger>
  <level>WARNING</level>
  <class>Example</class>
  <method>main</method>
  <thread>1</thread>
  <message>Index 3 out of bounds for length 3</message>
</record>
</log>